cesnet_openid_remote/__init__.py
cesnet_openid_remote/communities.py
cesnet_openid_remote/remote.py
cesnet_openid_remote/version.py
cesnet_openid_remote-3.0.0.dist-info/AUTHORS.rst
cesnet_openid_remote-3.0.0.dist-info/LICENSE
cesnet_openid_remote-3.0.0.dist-info/METADATA
cesnet_openid_remote-3.0.0.dist-info/WHEEL
cesnet_openid_remote-3.0.0.dist-info/top_level.txt
cesnet_openid_remote-3.0.0.dist-info/RECORD
