Metadata-Version: 2.1
Name: cesnet-openid-remote
Version: 3.0.0
Summary: CESNET OIDC Auth backend for OARepo
License-File: LICENSE
License-File: AUTHORS.rst
Requires-Dist: oarepo-communities
Provides-Extra: devs
Requires-Dist: check-manifest ; extra == 'devs'
Provides-Extra: tests
Requires-Dist: pytest-invenio ; extra == 'tests'
Requires-Dist: oarepo <12,>=11 ; extra == 'tests'
